MANIFEST.in
README.rst
setup.py
versiontools_support.py
PyChef_PortableRSA.egg-info/PKG-INFO
PyChef_PortableRSA.egg-info/SOURCES.txt
PyChef_PortableRSA.egg-info/dependency_links.txt
PyChef_PortableRSA.egg-info/not-zip-safe
PyChef_PortableRSA.egg-info/requires.txt
PyChef_PortableRSA.egg-info/top_level.txt
chef/__init__.py
chef/api.py
chef/auth.py
chef/base.py
chef/client.py
chef/data_bag.py
chef/environment.py
chef/exceptions.py
chef/fabric.py
chef/key.py
chef/node.py
chef/role.py
chef/search.py
chef/tests/__init__.py
chef/tests/test_api.py
chef/tests/test_client.py
chef/tests/test_data_bag.py
chef/tests/test_environment.py
chef/tests/test_fabric.py
chef/tests/test_key.py
chef/tests/test_node.py
chef/tests/test_role.py
chef/tests/test_search.py
chef/utils/__init__.py
chef/utils/file.py
chef/utils/json.py