Metadata-Version: 1.1
Name: PyChef-PortableRSA
Version: 0.2.4.dev0
Summary: Python implementation of a Chef API client.
Home-page: http://github.com/coderanger/pychef
Author: Noah Kantrowitz
Author-email: noah@coderanger.net
License: BSD
Platform: UNKNOWN
Classifier: Development Status :: 5 - Production/Stable
Classifier: License :: OSI Approved :: BSD License
Classifier: Natural Language :: English
Classifier: Operating System :: OS Independent
Classifier: Programming Language :: Python
